setup.py
PyCitibike.egg-info/PKG-INFO
PyCitibike.egg-info/SOURCES.txt
PyCitibike.egg-info/dependency_links.txt
PyCitibike.egg-info/requires.txt
PyCitibike.egg-info/top_level.txt
pycitibike/__init__.py