Metadata-Version: 1.0
Name: PyCitibike
Version: 0.0.1
Summary: A Python API wrapper for the Citibike API
Home-page: http://github.com/codingjester/pycitibike
Author: John Bunting
Author-email: codingjester@gmail.com
License: MIT
Platform: UNKNOWN
